wslconv/__init__.py
wslconv/wslconv.py
wslconv-0.0.1.dist-info/LICENSE
wslconv-0.0.1.dist-info/METADATA
wslconv-0.0.1.dist-info/WHEEL
wslconv-0.0.1.dist-info/top_level.txt
wslconv-0.0.1.dist-info/RECORD
