Metadata-Version: 2.1
Name: wslconv
Version: 0.0.1
Summary: A utility for converting file paths between WSL and Windows formats
Author: Lasha Koroshinadze
License: MIT License
Project-URL: Homepage, https://github.com/lashahub/wslconv
Keywords: WSL,Windows Subsystem for Linux,Path conversion,Filesystem utilities,Windows and Linux interoperability,Cross-platform paths,Path translation
Classifier: Programming Language :: Python :: 3
Classifier: License :: OSI Approved :: MIT License
Classifier: Operating System :: OS Independent
Requires-Python: >=3.6
License-File: LICENSE
